{"cameraMode":{"drawMode":0,"name":"Shaded","section":"Shading Mode"},"sceneLighting":true,"audioPlay":false,"sceneViewState":{"m_AlwaysRefresh":false,"showFog":true,"showSkybox":true,"showFlares":true,"showImageEffects":true,"showParticleSystems":true,"showVisualEffectGraphs":true,"m_FxEnabled":true},"in2DMode":false,"pivot":{"x":-6.924154758453369,"y":-3.5384066104888918,"z":0.6041067242622376},"rotation":{"x":0.10368374735116959,"y":-0.8787182569503784,"z":0.22259995341300965,"w":0.4093194603919983},"size":8.788941383361817,"orthographic":false}